netbox_agent/__init__.py
netbox_agent/cli.py
netbox_agent/config.py
netbox_agent/dmidecode.py
netbox_agent/ethtool.py
netbox_agent/inventory.py
netbox_agent/ipmi.py
netbox_agent/lldp.py
netbox_agent/location.py
netbox_agent/logging.py
netbox_agent/lshw.py
netbox_agent/misc.py
netbox_agent/network.py
netbox_agent/power.py
netbox_agent/server.py
netbox_agent/virtualmachine.py
netbox_agent/drivers/__init__.py
netbox_agent/drivers/cmd.py
netbox_agent/drivers/file.py
netbox_agent/raid/__init__.py
netbox_agent/raid/base.py
netbox_agent/raid/hp.py
netbox_agent/raid/omreport.py
netbox_agent/raid/storcli.py
netbox_agent/vendors/__init__.py
netbox_agent/vendors/dell.py
netbox_agent/vendors/generic.py
netbox_agent/vendors/hp.py
netbox_agent/vendors/qct.py
netbox_agent/vendors/supermicro.py
netbox_agent-1.0.0.dist-info/LICENSE
netbox_agent-1.0.0.dist-info/METADATA
netbox_agent-1.0.0.dist-info/WHEEL
netbox_agent-1.0.0.dist-info/entry_points.txt
netbox_agent-1.0.0.dist-info/top_level.txt
netbox_agent-1.0.0.dist-info/RECORD
