Metadata-Version: 2.1
Name: netbox_agent
Version: 1.0.0
Summary: NetBox agent for server
Home-page: https://github.com/solvik/netbox_agent
Author: Solvik Blum
Author-email: solvik@solvik.fr
License: Apache2
Keywords: netbox
Classifier: Intended Audience :: Developers
Classifier: Development Status :: 5 - Production/Stable
Classifier: Programming Language :: Python :: 3
Classifier: Programming Language :: Python :: 3.7
Classifier: Programming Language :: Python :: 3.8
Classifier: Programming Language :: Python :: 3.9
Classifier: Programming Language :: Python :: 3.10
Classifier: Programming Language :: Python :: 3.11
Classifier: Programming Language :: Python :: 3.12
Classifier: Programming Language :: Python :: 3.13
License-File: LICENSE
Requires-Dist: pynetbox ==7.3.4
Requires-Dist: netaddr ==1.3.0
Requires-Dist: netifaces2 ==0.0.22
Requires-Dist: pyyaml ==6.0.1
Requires-Dist: jsonargparse ==4.32.0
Requires-Dist: python-slugify ==8.0.4
Requires-Dist: packaging ==23.2
Requires-Dist: distro ==1.9.0
